mits_similarity_3/__init__.py
mits_similarity_3/hamming_distance.py
mits_similarity_3/jaccard_coefficient.py
mits_similarity_3/overlap_coefficient.py
mits_similarity_3-0.1.dist-info/LICENSE
mits_similarity_3-0.1.dist-info/METADATA
mits_similarity_3-0.1.dist-info/WHEEL
mits_similarity_3-0.1.dist-info/top_level.txt
mits_similarity_3-0.1.dist-info/RECORD
